django_object_toolbar_admin/__init__.py
django_object_toolbar_admin/admin.py
django_object_toolbar_admin/apps.py
django_object_toolbar_admin/models.py
django_object_toolbar_admin/tests.py
django_object_toolbar_admin/views.py
django_object_toolbar_admin/locale/zh_Hans/LC_MESSAGES/django.mo
django_object_toolbar_admin/locale/zh_Hans/LC_MESSAGES/django.po
django_object_toolbar_admin/migrations/__init__.py
django_object_toolbar_admin/templates/admin/change_form_object_tools.html
django_object_toolbar_admin/templates/django-object-toolbar-admin/object-toolbar.html
django_object_toolbar_admin-0.1.3.dist-info/licenses/LICENSE
django_object_toolbar_admin-0.1.3.dist-info/METADATA
django_object_toolbar_admin-0.1.3.dist-info/WHEEL
django_object_toolbar_admin-0.1.3.dist-info/top_level.txt
django_object_toolbar_admin-0.1.3.dist-info/RECORD
